.coveragerc
.gitattributes
.travis.yml
AUTHORS.rst
CHANGES.rst
LICENSE.txt
README.rst
deploy.py
pytest.ini
requirements.txt
setup.cfg
setup.py
test-requirements.txt
tox.ini
.benchmarks/Linux-CPython-3.6-64bit/0029_fb41cfedbba50666704233fc17ae12e2ad2815d1_20170208_091956_uncommitted-changes.json
.benchmarks/Linux-CPython-3.6-64bit/0030_79ce88376ed0193a2a45d659d2779ce2ef3e8be0_20170208_132801_uncommitted-changes.json
.benchmarks/Linux-CPython-3.6-64bit/0031_d600607e839d76cafabd7efa10eb990e1d3e7613_20170208_164719_uncommitted-changes.json
.benchmarks/Linux-CPython-3.6-64bit/0032_f0262e2f40cf206f70feeaeed30569742f617008_20170208_211503_uncommitted-changes.json
.benchmarks/Linux-CPython-3.6-64bit/0033_d8b34eb821b887994b209e3c2cbfcc9f30e42f5a_20170208_211839_uncommitted-changes.json
.benchmarks/Linux-CPython-3.6-64bit/0034_659ae909db49994292e93c1fe59579caac6da34c_20170208_212610_uncommitted-changes.json
.benchmarks/Linux-CPython-3.6-64bit/0035_f41c0c0069558e6032572b5fe5a66b1544c0c085_20170209_214739_uncommitted-changes.json
.benchmarks/Linux-CPython-3.6-64bit/0036_f5f2b6d7b345b5c17bdee68afbd1a0e2698a4cb6_20170210_123823_uncommitted-changes.json
.benchmarks/Linux-CPython-3.6-64bit/0037_60e3cd865b4f89dba6ed7c865fd87920a9517487_20170210_130156_uncommitted-changes.json
.benchmarks/Linux-CPython-3.6-64bit/0038_6673c64aa324ac2e294635efe81dba286cee4cc6_20170213_220251_uncommitted-changes.json
.benchmarks/Linux-CPython-3.6-64bit/0039_353eba1f7a47e7a3ececdac4d75118d41d3262a2_20170213_221020_uncommitted-changes.json
.benchmarks/Linux-CPython-3.6-64bit/0040_e1253f50df8c9cc4f04ee6debd1584d6e36aa62e_20170213_221346_uncommitted-changes.json
.benchmarks/Linux-CPython-3.6-64bit/0041_23743f8b15975dd0aebdd76d54c0dd2b2d419953_20170213_221631_uncommitted-changes.json
.benchmarks/Linux-CPython-3.6-64bit/0042_23743f8b15975dd0aebdd76d54c0dd2b2d419953_20170213_222340_uncommitted-changes.json
xsorted.egg-info/PKG-INFO
xsorted.egg-info/SOURCES.txt
xsorted.egg-info/dependency_links.txt
xsorted.egg-info/not-zip-safe
xsorted.egg-info/requires.txt
xsorted.egg-info/top_level.txt