Metadata-Version: 1.1
Name: xsorted
Version: 0.0.4
Summary: Like sorted but using external sorting so that large data sets can be sorted.
Home-page: https://github.com/moagstar/xsorted
Author: Daniel Bradburn
Author-email: moagstar@gmail.com
License: MIT
Platform: UNKNOWN
Classifier: Development Status :: 4 - Beta
Classifier: Programming Language :: Python
